onnx_modifier/__init__.py
onnx_modifier/app.py
onnx_modifier/app_desktop.py
onnx_modifier/onnx_modifier.py
onnx_modifier/static/app.js
onnx_modifier/static/base.js
onnx_modifier/static/dagre.js
onnx_modifier/static/electron.js
onnx_modifier/static/favicon.png
onnx_modifier/static/flatbuffers.js
onnx_modifier/static/gzip.js
onnx_modifier/static/index.js
onnx_modifier/static/json.js
onnx_modifier/static/logo.svg
onnx_modifier/static/modifier.js
onnx_modifier/static/npyjs.js
onnx_modifier/static/numpy.js
onnx_modifier/static/onnx-metadata.json
onnx_modifier/static/onnx-proto.js
onnx_modifier/static/onnx-schema.js
onnx_modifier/static/onnx.js
onnx_modifier/static/pickle.js
onnx_modifier/static/protobuf.js
onnx_modifier/static/python.js
onnx_modifier/static/sweetalert.css
onnx_modifier/static/sweetalert.min.js
onnx_modifier/static/tar.js
onnx_modifier/static/text.js
onnx_modifier/static/view-grapher.css
onnx_modifier/static/view-grapher.js
onnx_modifier/static/view-sidebar.css
onnx_modifier/static/view-sidebar.js
onnx_modifier/static/view.js
onnx_modifier/static/xml.js
onnx_modifier/static/zip.js
onnx_modifier/templates/electron.html
onnx_modifier/templates/index.html
onnx_modifier/utils/__init__.py
onnx_modifier/utils/builders.py
onnx_modifier/utils/parse_tools.py
onnx_modifier/utils/thrid_party_tools.py
onnx_modifier/utils/toposort.py
onnx_modifier-1.0.0.dist-info/entry_points.txt
onnx_modifier-1.0.0.dist-info/WHEEL
onnx_modifier-1.0.0.dist-info/METADATA
onnx_modifier-1.0.0.dist-info/RECORD
