Metadata-Version: 2.3
Name: onnx-modifier
Version: 1.0.0
Summary: A tool to modify ONNX models in a visualization fashion, based on Netron and Flask.
Author-email: Zhang Ge <sjtu.zg123@gmail.com>
Requires-Dist: onnx==1.13.0
Requires-Dist: flask==2.2.5
Requires-Dist: onnx-tool==0.8.1
Project-URL: Homepage, https://github.com/ZhangGe6/onnx-modifier
Project-URL: Issues, https://github.com/ZhangGe6/onnx-modifier/issues
